{
  "config": {
    "chainId": 1337,
    "homesteadBlock": 0,
    "eip150Block": 0,
    "eip155Block": 0,
    "eip158Block": 0,
    "byzantiumBlock": 0,
    "constantinopleBlock": 0,
    "petersburgBlock": 0,
    "istanbulBlock": 0,
    "berlinBlock": 0,
    "londonBlock": 0,
    "terminalTotalDifficulty": 0,
    "terminalTotalDifficultyPassed": true,
    "shanghaiTime": 0,
    "cancunTime": 0
  },
  "difficulty": "0x0",
  "gasLimit": "0x3938700",
  "baseFeePerGas": "0xF4240",
  "alloc": {
    "0xf39Fd6e51aad88F6F4ce6aB8827279cffFb92266": {
      "balance": "0x200000000000000000000000000000000000000000000000000000000000000"
    }
  }
}
